assignment4/A4Q1_one_bit_adder.v
module one_bit_adder(a, b, c_in, opcode, sum, c_out);

    input a, b, c_in, opcode;
    output wire sum, c_out;

    wire b_t;

    assign b_t = b ^ opcode;
    assign sum = a ^ b_t ^ c_in;
    assign c_out = (a & b_t) || (b_t & c_in) || (a & c_in);

endmodule

assignment4/A4Q2_five_bit_adder.v
`include "A4Q1_one_bit_adder.v"

module five_bit_adder(A, B, opcode, sum, c_out, over); 

    input [4:0] A, B;
    input opcode;

    output wire [4:0] sum;
    output wire c_out, over;

    wire [4:0] c_mid;

    one_bit_adder ADDER0(A[0], B[0], opcode, opcode, sum[0], c_mid[0]);
    one_bit_adder ADDER1(A[1], B[1], c_mid[0], opcode, sum[1], c_mid[1]);
    one_bit_adder ADDER2(A[2], B[2], c_mid[1], opcode, sum[2], c_mid[2]);
    one_bit_adder ADDER3(A[3], B[3], c_mid[2], opcode, sum[3], c_mid[3]);
    one_bit_adder ADDER4(A[4], B[4], c_mid[3], opcode, sum[4], c_mid[4]); 

    assign over = c_mid[4] ^ c_out;

endmodule

assignment4/A4_Q2_worm.v
`include "A4Q2_five_bit_adder.v"

module worm(in,clk,out1,out2,in_valid);

    input in_valid;
    input [3:0] in;
    input clk;

    output wire[4:0] out1, out2;    
    
    reg[4:0] state[1:0];
    wire[4:0] buff;
    
    reg[1:0] direction, steps;    
    wire overflow, c_out;
    reg opcode;
    reg[4:0] A, B;

    five_bit_adder ADDER(A, B, opcode, buff, c_out, overflow);

    initial begin
        state[0] <= 5'd0;
        state[1] <= 5'd0; 
        A <= 5'd0;
        B <= 5'd0;
        opcode <= 1'd0;
        // buff <= 5'd0;
    end

    // 00 - N, 01 - E, 10 - S, 11 - W

    always @(posedge clk & in_valid) begin
        // direction <= {in[3], in[2]};
        A <= state[in[2]];
        B <= {in[1], in[0]};
        opcode <= in[3];
    
        // #1
/*         if(buff[4] == 1'b1) begin
            state[in[2]] <= {1'b0, {4{~in[3]}}};
        end
        else begin
            state[in[2]] <= buff;
        end

        #1
        $display("t = %d: in:%b State:{%d, %d}, buff=%b, A = %b, B = %b\n", $time, in, state[0], state[1], buff, A, B); */
    end

    always @(negedge clk & in_valid)begin
        if(buff[4] == 1'b1) begin
            state[in[2]] <= {1'b0, {4{~in[3]}}};
        end
        else begin
            state[in[2]] <= buff;
        end

        //$display("t = %d: in:%b State:{%d, %d}, buff=%b, A = %b, B = %b\n", $time, in, state[0], state[1], buff, A, B);
    end

    //  always @(posedge clk ) begin
    //     dir <= {in[3],in[2]};
    //     size <= {in[1],in[0]};
    //     if(dir == 2'd0)begin
    //         // temp = state[0]+size;
    //         five_bit_adder ADDER(state[0], size, 1'b0, temp, c_out, overflow);
    //         //$display("temp = %d size = %d   ",temp,size);
    //         if(temp < 5'd15)begin
    //             state[0] <= temp;
    //             //$display("state[0] = %d\n",state[0]);
    //         end
    //         else begin
    //             state[0] <= 5'd15;
    //         end
    //     end

    //     else if(dir == 2'd1)begin
    //         // temp = state[1]+size;
    //                     five_bit_adder ADDER(state[1], size, 1'b0, temp, c_out, overflow);
    //         if(temp < 5'd15)begin
    //             state[1] <= temp;
    //         end
    //         else begin
    //             state[1] <= 5'd15;
    //         end
    //     end
    //     else if(dir == 2'd2)begin
    //         // temp = state[0]-size;
    //         five_bit_adder ADDER(state[0], size, 1'b1, temp, c_out, overflow);
    //         if(temp <5'd15)begin
    //             state[0] <= temp;
    //         end
    //         else begin
    //             state[0] <= 5'd0;
    //         end
    //     end 
    //     else begin
    //         // temp = state[1] - size;
    //         five_bit_adder ADDER(state[1], size, 1'b1, temp, c_out, overflow);
    //         if(temp <5'd15)begin
    //             state[1] <= temp;
    //         end
    //         else begin
    //             state[1] <= 5'd0;
    //         end
    //     end
    //  end

     assign out1 = state[0];
     assign out2 = state[1];



endmodule

assignment4/A4_Q2_wormtop.v
`include "A4_Q2_worm.v"

module worm_top;
    reg clk;
    reg[3:0] in;
    wire[4:0] out1;
    wire[4:0] out2;
    reg in_valid;

    worm a(in,clk,out1,out2,in_valid);

    always @(negedge clk) begin
        $display("t = %d: Co-ordinates = (%d,%d)", $time, out1,out2);

    end

    always begin
        #5
        clk <= ~clk;
    end

    initial begin
        clk <= 1'b1;
        in_valid=1;
        #10
        in_valid=1;
        #200
        $finish;
    end  

    initial begin
        in <= 4'b0010;
        #10
        in <= 4'b0011;
        #10
        in <= 4'b0111;
        #10
        in <= 4'b1011;
        #10
        in <= 4'b1111;
        #10
        in <= 4'b0011;
        #10
        in <= 4'b1111;
        #20
        $finish;
    end

    initial begin
        $dumpfile("worm.vcd");
        $dumpvars(0,worm_top);
    end


endmodule

assignment4/worm.vcd
$date
	Thu Feb 18 21:50:17 2021
$end
$version
	Icarus Verilog
$end
$timescale
	1s
$end
$scope module worm_top $end
$var wire 5 ! out2 [4:0] $end
$var wire 5 " out1 [4:0] $end
$var reg 1 # clk $end
$var reg 4 $ in [3:0] $end
$var reg 1 % in_valid $end
$scope module a $end
$var wire 1 & c_out $end
$var wire 1 # clk $end
$var wire 4 ' in [3:0] $end
$var wire 1 % in_valid $end
$var wire 5 ( out1 [4:0] $end
$var wire 5 ) out2 [4:0] $end
$var wire 1 * overflow $end
$var wire 5 + buff [4:0] $end
$var reg 5 , A [4:0] $end
$var reg 5 - B [4:0] $end
$var reg 1 . opcode $end
$scope module ADDER $end
$var wire 5 / A [4:0] $end
$var wire 5 0 B [4:0] $end
$var wire 1 & c_out $end
$var wire 1 . opcode $end
$var wire 1 * over $end
$var wire 5 1 sum [4:0] $end
$var wire 5 2 c_mid [4:0] $end
$scope module ADDER0 $end
$var wire 1 3 a $end
$var wire 1 4 b $end
$var wire 1 5 b_t $end
$var wire 1 . c_in $end
$var wire 1 6 c_out $end
$var wire 1 . opcode $end
$var wire 1 7 sum $end
$upscope $end
$scope module ADDER1 $end
$var wire 1 8 a $end
$var wire 1 9 b $end
$var wire 1 : b_t $end
$var wire 1 ; c_in $end
$var wire 1 < c_out $end
$var wire 1 . opcode $end
$var wire 1 = sum $end
$upscope $end
$scope module ADDER2 $end
$var wire 1 > a $end
$var wire 1 ? b $end
$var wire 1 @ b_t $end
$var wire 1 A c_in $end
$var wire 1 B c_out $end
$var wire 1 . opcode $end
$var wire 1 C sum $end
$upscope $end
$scope module ADDER3 $end
$var wire 1 D a $end
$var wire 1 E b $end
$var wire 1 F b_t $end
$var wire 1 G c_in $end
$var wire 1 H c_out $end
$var wire 1 . opcode $end
$var wire 1 I sum $end
$upscope $end
$scope module ADDER4 $end
$var wire 1 J a $end
$var wire 1 K b $end
$var wire 1 L b_t $end
$var wire 1 M c_in $end
$var wire 1 N c_out $end
$var wire 1 . opcode $end
$var wire 1 O sum $end
$upscope $end
$upscope $end
$upscope $end
$upscope $end
$enddefinitions $end
#0
$dumpvars
0O
0N
0M
0L
0K
0J
0I
0H
0G
0F
0E
0D
0C
0B
0A
0@
0?
0>
1=
0<
0;
1:
19
08
07
06
05
04
03
b0 2
b10 1
b10 0
b0 /
0.
b10 -
b0 ,
b10 +
x*
b0 )
b0 (
b10 '
z&
1%
b10 $
1#
b0 "
b0 !
$end
#5
b10 "
b10 (
0#
#10
1C
1A
17
b10 2
1<
b101 +
b101 1
0=
15
14
18
b11 -
b11 0
b10 ,
b10 /
1#
b11 $
b11 '
#15
b101 "
b101 (
0#
#20
0C
0A
b0 2
0<
b11 +
b11 1
1=
08
b0 ,
b0 /
1#
b111 $
b111 '
#25
b11 !
b11 )
0#
#30
1N
1M
1H
1G
1B
1;
1=
0I
0O
b11101 2
16
05
b10 +
b10 1
07
0:
1@
1F
1L
13
1>
1.
b101 ,
b101 /
1#
b1011 $
b1011 '
#35
b10 "
b10 (
0#
#40
1N
0O
1M
1H
0I
1G
1A
1B
0=
b11111 2
1<
b0 +
b0 1
0C
18
0>
b11 ,
b11 /
1#
b1111 $
b1111 '
#45
b0 !
b0 )
0#
#50
0G
0M
0B
0H
0N
0;
0=
1C
0I
0O
b10 2
06
15
b101 +
b101 1
17
1:
0@
0F
0L
03
0.
b10 ,
b10 /
1#
b11 $
b11 '
#55
b101 "
b101 (
0#
#60
0N
0M
0H
0=
0G
0A
0;
0B
0<
b0 2
06
1C
1I
1O
05
b11101 +
b11101 1
17
0:
1@
1F
1L
08
1.
b0 ,
b0 /
1#
b1111 $
b1111 '
