assignment11/A11Q2_div.v
module divider(done,clk,old_remainder,old_quotient,old_divisor,old_counter,divider_size,dividend_size,new_remainder,new_quotient,new_divisor,new_counter,status);
    input [31:0] old_remainder,old_quotient,old_divisor;
    input [4:0]divider_size,dividend_size,old_counter;
    input clk,done;
    output reg [31:0] new_remainder,new_quotient,new_divisor;
    output reg [4:0] new_counter;
    output reg status;

    initial begin
        status <= 1'b0;
    end

    always @(posedge clk ) begin
        if(done == 1'b0)begin
            status <= 1'b1;
            if(dividend_size - divider_size > 0)begin
                new_remainder <= old_remainder;
                new_divisor <= (old_divisor << (dividend_size - divider_size));
                new_quotient <= old_quotient;
                new_counter <= old_counter;
            end
        end
        else if(done == 1'b1)begin
            if ((old_counter < (dividend_size - divider_size ))&& (status ==1'b1))begin
                new_divisor <= old_divisor >> 1;
                new_counter <= old_counter+1;
                if(old_remainder[31] == 1'b1)begin
                    new_remainder <= old_remainder + old_divisor;
                    new_quotient = (old_quotient^(32'd1))<<1;
                    new_quotient[0] = 1'b1;
                end
                else if(old_remainder[31] == 1'b0)begin
                    new_remainder <= old_remainder - old_divisor;
                    new_quotient = (old_quotient << 1);
                    new_quotient[0] = 1'b1;
                end
            end
            else if((old_counter >= (dividend_size - divider_size)) && (status ==1'b1) )begin
                if(old_remainder[31] == 1'b1)begin
                    new_remainder <= old_remainder + old_divisor;
                    new_quotient <= (old_quotient^(32'd1));
                    new_counter <= old_counter+1;
                    new_divisor <= old_divisor;
                    $display("Extra round entered");
                end
                else if(old_remainder[31] == 1'b0)begin
                    new_remainder <= old_remainder;
                    new_quotient <= old_quotient;
                    new_counter <= old_counter+1;
                    new_divisor <= old_divisor;
                    status <=1'b0;
                end
            end
            else begin
                status <= 1'b0;
            end
        end
    end



endmodule

assignment11/A11Q2_top.v
`include "A11Q2_div.v"

module div_top;

    reg [31:0] old_remainder,old_quotient,old_divisor;
    reg [4:0]divider_size,dividend_size,old_counter;
    reg clk,done;
    wire [31:0] new_remainder,new_quotient,new_divisor;
    wire [4:0] new_counter;
    wire status;


    divider div(done,clk,old_remainder,old_quotient,old_divisor,old_counter,divider_size,dividend_size,new_remainder,new_quotient,new_divisor,new_counter,status);


    always @(negedge clk ) begin
            old_remainder <= new_remainder;
            old_divisor <= new_divisor;
            old_counter <= new_counter;
            old_quotient <= new_quotient;
        if(status == 1'b1)begin
            $display("t = %d: Divisor= %d Remainder = %d  Quotient = %d Count = %d",$time,new_divisor,$signed(new_remainder),new_quotient,new_counter);
        end
    end

    initial begin
        clk <= 1'b1;
        done <= 1'b0;
    end

    initial begin
        forever begin
            #5   
            clk <= ~clk;
        end
    end

    initial begin
        
        old_remainder <= 32'd67;
        old_quotient <= 32'd0;
        old_divisor <= 32'd14;
        old_counter <= 5'd0;
        dividend_size <= 5'd7;
        divider_size <= 5'd4;
        #10
        done <= 1'b1;
        
/*         #95
        done <=1'b0;
        old_remainder <= 32'd99;
        old_quotient <= 32'd0;
        old_divisor <= 32'd15;
        old_counter <= 5'd0;
        dividend_size <= 5'd7;
        divider_size <= 5'd4;
        #5
        done <= 1'b1; */
    end

    initial begin
        #500
        $finish;
    end

        // gtkwave debugging

    initial begin
        $dumpfile("divide.vcd");
        $dumpvars(0, div_top);
    end 







endmodule

assignment11/divide.vcd
$date
	Sun May 02 20:12:49 2021
$end
$version
	Icarus Verilog
$end
$timescale
	1s
$end
$scope module div_top $end
$var wire 1 ! status $end
$var wire 32 " new_remainder [31:0] $end
$var wire 32 # new_quotient [31:0] $end
$var wire 32 $ new_divisor [31:0] $end
$var wire 5 % new_counter [4:0] $end
$var reg 1 & clk $end
$var reg 5 ' dividend_size [4:0] $end
$var reg 5 ( divider_size [4:0] $end
$var reg 1 ) done $end
$var reg 5 * old_counter [4:0] $end
$var reg 32 + old_divisor [31:0] $end
$var reg 32 , old_quotient [31:0] $end
$var reg 32 - old_remainder [31:0] $end
$scope module div $end
$var wire 1 & clk $end
$var wire 5 . dividend_size [4:0] $end
$var wire 5 / divider_size [4:0] $end
$var wire 1 ) done $end
$var wire 5 0 old_counter [4:0] $end
$var wire 32 1 old_divisor [31:0] $end
$var wire 32 2 old_quotient [31:0] $end
$var wire 32 3 old_remainder [31:0] $end
$var reg 5 4 new_counter [4:0] $end
$var reg 32 5 new_divisor [31:0] $end
$var reg 32 6 new_quotient [31:0] $end
$var reg 32 7 new_remainder [31:0] $end
$var reg 1 ! status $end
$upscope $end
$upscope $end
$enddefinitions $end
#0
$dumpvars
b1000011 7
b0 6
b1110000 5
b0 4
b1000011 3
b0 2
b1110 1
b0 0
b100 /
b111 .
b1000011 -
b0 ,
b1110 +
b0 *
0)
b100 (
b111 '
1&
b0 %
b1110000 $
b0 #
b1000011 "
1!
$end
#5
b1110000 +
b1110000 1
0&
#10
b11111111111111111111111111010011 "
b11111111111111111111111111010011 7
b1 %
b1 4
b111000 $
b111000 5
b1 #
b1 6
1&
1)
#15
b1 ,
b1 2
b1 *
b1 0
b111000 +
b111000 1
b11111111111111111111111111010011 -
b11111111111111111111111111010011 3
0&
#20
b1011 "
b1011 7
b10 %
b10 4
b11100 $
b11100 5
b1 #
b1 6
1&
#25
b10 *
b10 0
b11100 +
b11100 1
b1011 -
b1011 3
0&
#30
b11111111111111111111111111101111 "
b11111111111111111111111111101111 7
b11 %
b11 4
b1110 $
b1110 5
b11 #
b11 6
1&
#35
b11 ,
b11 2
b11 *
b11 0
b1110 +
b1110 1
b11111111111111111111111111101111 -
b11111111111111111111111111101111 3
0&
#40
b100 %
b100 4
b10 #
b10 6
b11111111111111111111111111111101 "
b11111111111111111111111111111101 7
1&
#45
b10 ,
b10 2
b100 *
b100 0
b11111111111111111111111111111101 -
b11111111111111111111111111111101 3
0&
#50
b101 %
b101 4
b11 #
b11 6
b1011 "
b1011 7
1&
#55
b11 ,
b11 2
b101 *
b101 0
b1011 -
b1011 3
0&
#60
0!
b110 %
b110 4
1&
#65
b110 *
b110 0
0&
