assignment11/A11Q2_div.v
module divider(done,clk,old_remainder,old_quotient,old_divisor,old_counter,divider_size,dividend_size,new_remainder,new_quotient,new_divisor,new_counter,status);
    input [31:0] old_remainder,old_quotient,old_divisor;
    input [4:0]divider_size,dividend_size,old_counter;
    input clk,done;
    output reg [31:0] new_remainder,new_quotient,new_divisor;
    output reg [4:0] new_counter;
    output reg status;

    initial begin
        status <= 1'b0;
    end

    always @(posedge clk ) begin
        if(done == 1'b0)begin
            if(divider_size - dividend_size > 0)begin
                new_remainder <= old_remainder;
                new_divisor <= (old_divisor << (divider_size - dividend_size));
                new_quotient <= old_quotient;
                new_counter <= old_counter;
            end
        end
        else if(done == 1'b1)begin
            status <= 1'b1;
            if (old_counter < (divider_size - dividend_size))begin
                new_divisor <= old_divisor >> 1;
                new_counter <= old_counter+1;
                if(old_remainder < 32'd0)begin
                    new_remainder <= old_remainder + old_divisor;
                    new_quotient <= ((old_quotient^(32'd1))<<1) || 32'd1;
                end
                else if(old_remainder >= 32'd0)begin
                    new_remainder <= old_remainder - old_divisor;
                    new_quotient <= (old_quotient << 1) || 32'd1;
                end
            end
            else if(old_counter == (divider_size - dividend_size))begin
                if(old_remainder < 32'd0)begin
                    new_remainder <= old_remainder + old_divisor;
                    new_quotient <= old_quotient^(32'd1);
                    new_counter <= old_counter+1;
                    new_divisor <= old_divisor;
                end
                else if(old_remainder >=32'd0)begin
                    new_remainder <= old_remainder;
                    new_quotient <= old_quotient;
                    new_counter <= old_counter+1;
                    new_divisor <= old_divisor;
                    status <= 1'b0;
                end
            end
            else begin
                status <= 1'b0;
            end
        end
    end



endmodule

assignment11/A11Q2_top.v
`include "A11Q2_div.v"

module div_top;

    reg [31:0] old_remainder,old_quotient,old_divisor;
    reg [4:0]divider_size,dividend_size,old_counter;
    reg clk,done;
    wire [31:0] new_remainder,new_quotient,new_divisor;
    wire [4:0] new_counter;
    wire status;

    divider div(clk,inp,dividend,dividend_length,divisor,divisor_length,quotient,remainder,add_count,sub_count,done);

    always @(negedge clk ) begin
        if(done ==1)begin
            if(index !=0)begin
                $display("Time =%d : Dividend = %d Divisor = %d Remainder = %d Quotient = %d Additions = %d Subtractions = %d",$time,dividend,divisor,remainder,quotient,add_count,sub_count);
            end
            index <= index+1;
            inp <= 1'b1;
            dividend <= dividend_list[index];
            divisor <= divisor_list[index];
            dividend_length <= dividend_length_list[index];
            divisor_length <= divisor_length_list[index];
            
        end
        else begin
            inp <= 1'b0;
        end

        if(index > 4'd10)begin
            $finish;
        end
    end

    initial begin
        clk <= 1'b1;
        done <= 1'b0;

        index <=1'b0;
        inp <= 1'b1;

        dividend_list[0] = 67;
        divisor_list[0] = 14;
        dividend_length_list[0] = 7;
        divisor_length_list[0] = 4;

        dividend_list[1] <= 68;
        divisor_list[1] <= 14;
        dividend_length_list[1] <= 7;
        divisor_length_list[1] <= 4;

        dividend_list[2] <= 99;
        divisor_list[2] <= 14;
        dividend_length_list[2] <= 7;
        divisor_length_list[2] <= 4;

        dividend_list[3] <= 13;
        divisor_list[3] <= 77;
        dividend_length_list[3] <= 4;
        divisor_length_list[3] <= 7;

        dividend_list[4] <= 87;
        divisor_list[4] <= 16;
        dividend_length_list[4] <= 7;
        divisor_length_list[4] <= 4;

        dividend_list[5] <= 78;
        divisor_list[5] <= 11;
        dividend_length_list[5] <= 7;
        divisor_length_list[5] <= 4;

        dividend_list[6] <= 57;
        divisor_list[6] <= 12;
        dividend_length_list[6] <= 6;
        divisor_length_list[6] <= 4;

        dividend_list[7] <= 67;
        divisor_list[7] <= 4;
        dividend_length_list[7] <= 7;
        divisor_length_list[7] <= 3;

        dividend_list[8] <= 6;
        divisor_list[8] <= 14;
        dividend_length_list[8] <= 3;
        divisor_length_list[8] <= 4;

        dividend_list[9] <= 156;
        divisor_list[9] <= 69;
        dividend_length_list[9] <= 8;
        divisor_length_list[9] <= 7;
    end

    initial begin
        forever begin
            #5   
            clk <= ~clk;
        end
    end

    // initial begin
    //     $dumpfile("div.top");
    //     $dumpvars(0, div_top);
    // end

endmodule

assignment11/divide.vcd
$date
	Sun May 02 21:02:06 2021
$end
$version
	Icarus Verilog
$end
$timescale
	1s
$end
$scope module div_top $end
$var wire 1 ! status $end
$var wire 32 " new_remainder [31:0] $end
$var wire 32 # new_quotient [31:0] $end
$var wire 32 $ new_divisor [31:0] $end
$var wire 5 % new_counter [4:0] $end
$var reg 1 & clk $end
$var reg 5 ' dividend_size [4:0] $end
$var reg 5 ( divider_size [4:0] $end
$var reg 1 ) done $end
$var reg 5 * old_counter [4:0] $end
$var reg 32 + old_divisor [31:0] $end
$var reg 32 , old_quotient [31:0] $end
$var reg 32 - old_remainder [31:0] $end
$scope module div $end
$var wire 1 & clk $end
$var wire 5 . dividend_size [4:0] $end
$var wire 5 / divider_size [4:0] $end
$var wire 1 ) done $end
$var wire 5 0 old_counter [4:0] $end
$var wire 32 1 old_divisor [31:0] $end
$var wire 32 2 old_quotient [31:0] $end
$var wire 32 3 old_remainder [31:0] $end
$var reg 5 4 new_counter [4:0] $end
$var reg 32 5 new_divisor [31:0] $end
$var reg 32 6 new_quotient [31:0] $end
$var reg 32 7 new_remainder [31:0] $end
$var reg 1 ! status $end
$upscope $end
$upscope $end
$enddefinitions $end
#0
$dumpvars
b1000011 7
b0 6
b1110000 5
b0 4
b1000011 3
b0 2
b1110 1
b0 0
b100 /
b111 .
b1000011 -
b0 ,
b1110 +
b0 *
0)
b100 (
b111 '
1&
b0 %
b1110000 $
b0 #
b1000011 "
1!
$end
#5
b1110000 +
b1110000 1
0&
#10
b11111111111111111111111111010011 "
b11111111111111111111111111010011 7
b1 %
b1 4
b111000 $
b111000 5
b1 #
b1 6
1&
1)
#15
b1 ,
b1 2
b1 *
b1 0
b111000 +
b111000 1
b11111111111111111111111111010011 -
b11111111111111111111111111010011 3
0&
#20
b1011 "
b1011 7
b10 %
b10 4
b11100 $
b11100 5
b1 #
b1 6
1&
#25
b10 *
b10 0
b11100 +
b11100 1
b1011 -
b1011 3
0&
#30
b11111111111111111111111111101111 "
b11111111111111111111111111101111 7
b11 %
b11 4
b1110 $
b1110 5
b1 #
b1 6
1&
#35
b11 *
b11 0
b1110 +
b1110 1
b11111111111111111111111111101111 -
b11111111111111111111111111101111 3
0&
#40
b11111111111111111111111111111101 "
b11111111111111111111111111111101 7
b100 %
b100 4
b111 $
b111 5
b1 #
b1 6
1&
#45
b100 *
b100 0
b111 +
b111 1
b11111111111111111111111111111101 -
b11111111111111111111111111111101 3
0&
#50
b101 %
b101 4
b0 #
b0 6
b100 "
b100 7
1&
#55
b0 ,
b0 2
b101 *
b101 0
b100 -
b100 3
0&
#60
0!
b110 %
b110 4
1&
#65
b110 *
b110 0
0&
